{
  "time": "2026-07-02T07:59:59.999000+00:00",
  "ranking": [
    {
      "rank": 1,
      "symbol": "SOL",
      "scanTime": "2026-07-02T07:59:59.999000+00:00",
      "btcReturn": -1.4776,
      "coinReturn": -0.924,
      "relativeScore": 0.5536,
      "cumulativeRelativeScore": 1.5617,
      "aiScore": 55.65,
      "score": 55.65,
      "volumeScore": 5.25,
      "trendScore": 71.36,
      "leadingScore": 91.67,
      "volatilityScore": 88.47,
      "top10Streak": 31,
      "top20Streak": 85
    },
    {
      "rank": 2,
      "symbol": "ETH",
      "scanTime": "2026-07-02T07:59:59.999000+00:00",
      "btcReturn": -1.4776,
      "coinReturn": -1.4248,
      "relativeScore": 0.0528,
      "cumulativeRelativeScore": 0.3422,
      "aiScore": 50.55,
      "score": 50.55,
      "volumeScore": 1.37,
      "trendScore": 56.02,
      "leadingScore": 90.0,
      "volatilityScore": 89.13,
      "top10Streak": 7,
      "top20Streak": 85
    },
    {
      "rank": 6,
      "symbol": "HYPE",
      "scanTime": "2026-07-02T07:59:59.999000+00:00",
      "btcReturn": -1.4776,
      "coinReturn": -0.7325,
      "relativeScore": 0.7451,
      "cumulativeRelativeScore": -1.7919,
      "aiScore": 47.46,
      "score": 47.46,
      "volumeScore": 0.44,
      "trendScore": 45.42,
      "leadingScore": 75.0,
      "volatilityScore": 85.64,
      "top10Streak": 4,
      "top20Streak": 85
    },
    {
      "rank": 16,
      "symbol": "SOXL",
      "scanTime": "2026-07-02T07:59:59.999000+00:00",
      "btcReturn": -1.4776,
      "coinReturn": -7.1919,
      "relativeScore": -5.7143,
      "cumulativeRelativeScore": -23.0896,
      "aiScore": 21.38,
      "score": 21.38,
      "volumeScore": 5.37,
      "trendScore": 29.74,
      "leadingScore": 71.43,
      "volatilityScore": 67.09,
      "top10Streak": 0,
      "top20Streak": 15
    },
    {
      "rank": 5,
      "symbol": "XRP",
      "scanTime": "2026-07-02T07:59:59.999000+00:00",
      "btcReturn": -1.4776,
      "coinReturn": -0.862,
      "relativeScore": 0.6156,
      "cumulativeRelativeScore": -0.7096,
      "aiScore": 49.03,
      "score": 49.03,
      "volumeScore": 6.19,
      "trendScore": 51.99,
      "leadingScore": 66.67,
      "volatilityScore": 91.23,
      "top10Streak": 4,
      "top20Streak": 85
    },
    {
      "rank": 11,
      "symbol": "SKHYNIX",
      "scanTime": "2026-07-02T07:59:59.999000+00:00",
      "btcReturn": -1.4776,
      "coinReturn": -5.7024,
      "relativeScore": -4.2248,
      "cumulativeRelativeScore": -16.363,
      "aiScore": 33.57,
      "score": 33.57,
      "volumeScore": 87.12,
      "trendScore": 7.01,
      "leadingScore": 66.67,
      "volatilityScore": 83.3,
      "top10Streak": 0,
      "top20Streak": 5
    },
    {
      "rank": 13,
      "symbol": "MU",
      "scanTime": "2026-07-02T07:59:59.999000+00:00",
      "btcReturn": -1.4776,
      "coinReturn": -2.84,
      "relativeScore": -1.3624,
      "cumulativeRelativeScore": -13.6624,
      "aiScore": 31.99,
      "score": 31.99,
      "volumeScore": 5.84,
      "trendScore": 16.99,
      "leadingScore": 66.67,
      "volatilityScore": 82.11,
      "top10Streak": 0,
      "top20Streak": 15
    },
    {
      "rank": 9,
      "symbol": "SPCX",
      "scanTime": "2026-07-02T07:59:59.999000+00:00",
      "btcReturn": -1.4776,
      "coinReturn": -1.5322,
      "relativeScore": -0.0546,
      "cumulativeRelativeScore": -11.9434,
      "aiScore": 40.0,
      "score": 40.0,
      "volumeScore": 0.0,
      "trendScore": 47.79,
      "leadingScore": 62.5,
      "volatilityScore": 81.09,
      "top10Streak": 15,
      "top20Streak": 15
    },
    {
      "rank": 12,
      "symbol": "DRAM",
      "scanTime": "2026-07-02T07:59:59.999000+00:00",
      "btcReturn": -1.4776,
      "coinReturn": -3.3138,
      "relativeScore": -1.8362,
      "cumulativeRelativeScore": -13.3136,
      "aiScore": 32.54,
      "score": 32.54,
      "volumeScore": 24.21,
      "trendScore": 14.25,
      "leadingScore": 60.0,
      "volatilityScore": 85.12,
      "top10Streak": 0,
      "top20Streak": 14
    },
    {
      "rank": 10,
      "symbol": "SNDK",
      "scanTime": "2026-07-02T07:59:59.999000+00:00",
      "btcReturn": -1.4776,
      "coinReturn": -2.8529,
      "relativeScore": -1.3754,
      "cumulativeRelativeScore": -13.2042,
      "aiScore": 34.31,
      "score": 34.31,
      "volumeScore": 5.96,
      "trendScore": 34.58,
      "leadingScore": 57.14,
      "volatilityScore": 80.16,
      "top10Streak": 1,
      "top20Streak": 14
    },
    {
      "rank": 4,
      "symbol": "MSTR",
      "scanTime": "2026-07-02T07:59:59.999000+00:00",
      "btcReturn": -1.4776,
      "coinReturn": -2.492,
      "relativeScore": -1.0144,
      "cumulativeRelativeScore": 6.4644,
      "aiScore": 49.27,
      "score": 49.27,
      "volumeScore": 0.0,
      "trendScore": 74.69,
      "leadingScore": 50.0,
      "volatilityScore": 71.19,
      "top10Streak": 1,
      "top20Streak": 1
    },
    {
      "rank": 15,
      "symbol": "KORU",
      "scanTime": "2026-07-02T07:59:59.999000+00:00",
      "btcReturn": -1.4776,
      "coinReturn": -7.6671,
      "relativeScore": -6.1895,
      "cumulativeRelativeScore": -23.3652,
      "aiScore": 25.51,
      "score": 25.51,
      "volumeScore": 100.0,
      "trendScore": 0.0,
      "leadingScore": 50.0,
      "volatilityScore": 65.28,
      "top10Streak": 0,
      "top20Streak": 4
    },
    {
      "rank": 8,
      "symbol": "XAG",
      "scanTime": "2026-07-02T07:59:59.999000+00:00",
      "btcReturn": -1.4776,
      "coinReturn": -1.474,
      "relativeScore": 0.0036,
      "cumulativeRelativeScore": -1.7353,
      "aiScore": 45.52,
      "score": 45.52,
      "volumeScore": 7.37,
      "trendScore": 54.18,
      "leadingScore": 45.45,
      "volatilityScore": 88.94,
      "top10Streak": 5,
      "top20Streak": 16
    },
    {
      "rank": 14,
      "symbol": "MRVL",
      "scanTime": "2026-07-02T07:59:59.999000+00:00",
      "btcReturn": -1.4776,
      "coinReturn": -3.7952,
      "relativeScore": -2.3176,
      "cumulativeRelativeScore": -12.544,
      "aiScore": 31.6,
      "score": 31.6,
      "volumeScore": 0.0,
      "trendScore": 43.56,
      "leadingScore": 40.0,
      "volatilityScore": 80.47,
      "top10Streak": 0,
      "top20Streak": 13
    },
    {
      "rank": 7,
      "symbol": "XAU",
      "scanTime": "2026-07-02T07:59:59.999000+00:00",
      "btcReturn": -1.4776,
      "coinReturn": -0.1288,
      "relativeScore": 1.3488,
      "cumulativeRelativeScore": -1.7724,
      "aiScore": 47.26,
      "score": 47.26,
      "volumeScore": 9.67,
      "trendScore": 50.82,
      "leadingScore": 33.33,
      "volatilityScore": 94.16,
      "top10Streak": 7,
      "top20Streak": 16
    },
    {
      "rank": 3,
      "symbol": "TAIKO",
      "scanTime": "2026-07-02T07:59:59.999000+00:00",
      "btcReturn": -1.4776,
      "coinReturn": -38.159,
      "relativeScore": -36.6814,
      "cumulativeRelativeScore": 195.5195,
      "aiScore": 49.5,
      "score": 49.5,
      "volumeScore": 100.0,
      "trendScore": 100.0,
      "leadingScore": 0.0,
      "volatilityScore": 0.0,
      "top10Streak": 4,
      "top20Streak": 4
    }
  ]
}
