{
  "time": "2026-07-13T23:59:59.999000+00:00",
  "ranking": [
    {
      "rank": 1,
      "symbol": "CL",
      "scanTime": "2026-07-13T23:59:59.999000+00:00",
      "btcReturn": 0.0822,
      "coinReturn": 1.5753,
      "relativeScore": 1.4931,
      "cumulativeRelativeScore": 6.7443,
      "aiScore": 57.0,
      "score": 57.0,
      "volumeScore": 47.2,
      "trendScore": 68.57,
      "leadingScore": 7.69,
      "volatilityScore": 91.57,
      "top10Streak": 13,
      "top20Streak": 13
    },
    {
      "rank": 2,
      "symbol": "ETH",
      "scanTime": "2026-07-13T23:59:59.999000+00:00",
      "btcReturn": 0.0822,
      "coinReturn": 0.1167,
      "relativeScore": 0.0345,
      "cumulativeRelativeScore": 0.5365,
      "aiScore": 51.4,
      "score": 51.4,
      "volumeScore": 11.98,
      "trendScore": 48.61,
      "leadingScore": 95.0,
      "volatilityScore": 93.66,
      "top10Streak": 33,
      "top20Streak": 149
    },
    {
      "rank": 3,
      "symbol": "XRP",
      "scanTime": "2026-07-13T23:59:59.999000+00:00",
      "btcReturn": 0.0822,
      "coinReturn": 0.0094,
      "relativeScore": -0.0728,
      "cumulativeRelativeScore": 0.2746,
      "aiScore": 48.73,
      "score": 48.73,
      "volumeScore": 19.45,
      "trendScore": 40.33,
      "leadingScore": 76.19,
      "volatilityScore": 94.72,
      "top10Streak": 3,
      "top20Streak": 13
    },
    {
      "rank": 4,
      "symbol": "SOL",
      "scanTime": "2026-07-13T23:59:59.999000+00:00",
      "btcReturn": 0.0822,
      "coinReturn": -0.2648,
      "relativeScore": -0.347,
      "cumulativeRelativeScore": -0.3941,
      "aiScore": 47.47,
      "score": 47.47,
      "volumeScore": 12.64,
      "trendScore": 39.18,
      "leadingScore": 84.21,
      "volatilityScore": 94.4,
      "top10Streak": 29,
      "top20Streak": 149
    },
    {
      "rank": 5,
      "symbol": "XAG",
      "scanTime": "2026-07-13T23:59:59.999000+00:00",
      "btcReturn": 0.0822,
      "coinReturn": -0.1385,
      "relativeScore": -0.2207,
      "cumulativeRelativeScore": -0.1946,
      "aiScore": 46.14,
      "score": 46.14,
      "volumeScore": 16.48,
      "trendScore": 39.8,
      "leadingScore": 60.0,
      "volatilityScore": 96.34,
      "top10Streak": 5,
      "top20Streak": 5
    },
    {
      "rank": 6,
      "symbol": "HYPE",
      "scanTime": "2026-07-13T23:59:59.999000+00:00",
      "btcReturn": 0.0822,
      "coinReturn": -0.3864,
      "relativeScore": -0.4686,
      "cumulativeRelativeScore": -4.099,
      "aiScore": 46.07,
      "score": 46.07,
      "volumeScore": 30.7,
      "trendScore": 33.03,
      "leadingScore": 76.92,
      "volatilityScore": 92.98,
      "top10Streak": 3,
      "top20Streak": 6
    },
    {
      "rank": 7,
      "symbol": "XAU",
      "scanTime": "2026-07-13T23:59:59.999000+00:00",
      "btcReturn": 0.0822,
      "coinReturn": -0.0277,
      "relativeScore": -0.1099,
      "cumulativeRelativeScore": -0.6604,
      "aiScore": 45.76,
      "score": 45.76,
      "volumeScore": 12.76,
      "trendScore": 42.93,
      "leadingScore": 54.55,
      "volatilityScore": 97.77,
      "top10Streak": 6,
      "top20Streak": 6
    },
    {
      "rank": 8,
      "symbol": "LAB",
      "scanTime": "2026-07-13T23:59:59.999000+00:00",
      "btcReturn": 0.0822,
      "coinReturn": 14.8649,
      "relativeScore": 14.7826,
      "cumulativeRelativeScore": -40.6077,
      "aiScore": 45.1,
      "score": 45.1,
      "volumeScore": 4.06,
      "trendScore": 0.0,
      "leadingScore": 80.0,
      "volatilityScore": 12.35,
      "top10Streak": 1,
      "top20Streak": 3
    },
    {
      "rank": 9,
      "symbol": "ZEC",
      "scanTime": "2026-07-13T23:59:59.999000+00:00",
      "btcReturn": 0.0822,
      "coinReturn": -1.6306,
      "relativeScore": -1.7128,
      "cumulativeRelativeScore": -4.1143,
      "aiScore": 43.69,
      "score": 43.69,
      "volumeScore": 32.81,
      "trendScore": 55.31,
      "leadingScore": 40.0,
      "volatilityScore": 89.12,
      "top10Streak": 1,
      "top20Streak": 13
    },
    {
      "rank": 10,
      "symbol": "MU",
      "scanTime": "2026-07-13T23:59:59.999000+00:00",
      "btcReturn": 0.0822,
      "coinReturn": -1.7257,
      "relativeScore": -1.8079,
      "cumulativeRelativeScore": -0.0863,
      "aiScore": 41.63,
      "score": 41.63,
      "volumeScore": 12.05,
      "trendScore": 34.3,
      "leadingScore": 68.75,
      "volatilityScore": 90.13,
      "top10Streak": 5,
      "top20Streak": 5
    }
  ]
}
