{
  "time": "2026-06-25T19:59:59.999000+00:00",
  "ranking": [
    {
      "rank": 1,
      "symbol": "SNDK",
      "scanTime": "2026-06-25T19:59:59.999000+00:00",
      "btcReturn": -0.4014,
      "coinReturn": 5.1913,
      "relativeScore": 5.5927,
      "cumulativeRelativeScore": 11.1309,
      "aiScore": 73.89,
      "score": 73.89,
      "volumeScore": 34.39,
      "trendScore": 64.09,
      "leadingScore": 100.0,
      "volatilityScore": 69.22,
      "top10Streak": 11,
      "top20Streak": 17
    },
    {
      "rank": 2,
      "symbol": "SLX",
      "scanTime": "2026-06-25T19:59:59.999000+00:00",
      "btcReturn": -0.4014,
      "coinReturn": 0.6821,
      "relativeScore": 1.0835,
      "cumulativeRelativeScore": 21.6734,
      "aiScore": 68.48,
      "score": 68.48,
      "volumeScore": 42.39,
      "trendScore": 100.0,
      "leadingScore": 50.0,
      "volatilityScore": 29.28,
      "top10Streak": 4,
      "top20Streak": 4
    },
    {
      "rank": 3,
      "symbol": "LITE",
      "scanTime": "2026-06-25T19:59:59.999000+00:00",
      "btcReturn": -0.4014,
      "coinReturn": 2.4142,
      "relativeScore": 2.8156,
      "cumulativeRelativeScore": 2.2065,
      "aiScore": 65.54,
      "score": 65.54,
      "volumeScore": 82.96,
      "trendScore": 54.04,
      "leadingScore": 66.67,
      "volatilityScore": 80.43,
      "top10Streak": 1,
      "top20Streak": 7
    },
    {
      "rank": 4,
      "symbol": "HYPE",
      "scanTime": "2026-06-25T19:59:59.999000+00:00",
      "btcReturn": -0.4014,
      "coinReturn": 2.7735,
      "relativeScore": 3.1749,
      "cumulativeRelativeScore": 2.3192,
      "aiScore": 62.86,
      "score": 62.86,
      "volumeScore": 56.34,
      "trendScore": 35.57,
      "leadingScore": 100.0,
      "volatilityScore": 81.45,
      "top10Streak": 4,
      "top20Streak": 54
    },
    {
      "rank": 5,
      "symbol": "SYN",
      "scanTime": "2026-06-25T19:59:59.999000+00:00",
      "btcReturn": -0.4014,
      "coinReturn": 2.3694,
      "relativeScore": 2.7708,
      "cumulativeRelativeScore": 25.667,
      "aiScore": 62.77,
      "score": 62.77,
      "volumeScore": 9.27,
      "trendScore": 100.0,
      "leadingScore": 0.0,
      "volatilityScore": 28.55,
      "top10Streak": 2,
      "top20Streak": 2
    },
    {
      "rank": 6,
      "symbol": "AAVE",
      "scanTime": "2026-06-25T19:59:59.999000+00:00",
      "btcReturn": -0.4014,
      "coinReturn": -1.498,
      "relativeScore": -1.0966,
      "cumulativeRelativeScore": 3.5475,
      "aiScore": 62.56,
      "score": 62.56,
      "volumeScore": 100.0,
      "trendScore": 79.76,
      "leadingScore": 50.0,
      "volatilityScore": 79.51,
      "top10Streak": 3,
      "top20Streak": 3
    },
    {
      "rank": 7,
      "symbol": "SOXL",
      "scanTime": "2026-06-25T19:59:59.999000+00:00",
      "btcReturn": -0.4014,
      "coinReturn": 2.6983,
      "relativeScore": 3.0997,
      "cumulativeRelativeScore": -0.8384,
      "aiScore": 60.31,
      "score": 60.31,
      "volumeScore": 73.73,
      "trendScore": 36.91,
      "leadingScore": 75.0,
      "volatilityScore": 58.13,
      "top10Streak": 1,
      "top20Streak": 19
    },
    {
      "rank": 8,
      "symbol": "MU",
      "scanTime": "2026-06-25T19:59:59.999000+00:00",
      "btcReturn": -0.4014,
      "coinReturn": 1.7426,
      "relativeScore": 2.144,
      "cumulativeRelativeScore": 3.0271,
      "aiScore": 59.72,
      "score": 59.72,
      "volumeScore": 19.49,
      "trendScore": 72.44,
      "leadingScore": 80.0,
      "volatilityScore": 63.54,
      "top10Streak": 6,
      "top20Streak": 17
    },
    {
      "rank": 9,
      "symbol": "SKHYNIX",
      "scanTime": "2026-06-25T19:59:59.999000+00:00",
      "btcReturn": -0.4014,
      "coinReturn": 0.6108,
      "relativeScore": 1.0122,
      "cumulativeRelativeScore": 4.6258,
      "aiScore": 56.31,
      "score": 56.31,
      "volumeScore": 2.48,
      "trendScore": 63.47,
      "leadingScore": 100.0,
      "volatilityScore": 70.87,
      "top10Streak": 5,
      "top20Streak": 14
    },
    {
      "rank": 10,
      "symbol": "DRAM",
      "scanTime": "2026-06-25T19:59:59.999000+00:00",
      "btcReturn": -0.4014,
      "coinReturn": 1.2715,
      "relativeScore": 1.6729,
      "cumulativeRelativeScore": -1.0048,
      "aiScore": 53.89,
      "score": 53.89,
      "volumeScore": 2.54,
      "trendScore": 56.99,
      "leadingScore": 100.0,
      "volatilityScore": 66.16,
      "top10Streak": 5,
      "top20Streak": 15
    }
  ]
}
