{
  "scanTime": "2026-07-17T11:59:59.999000+00:00",
  "items": [
    {
      "symbol": "SNDK",
      "relativeScore": 4.7797,
      "aiScore": 55.88
    },
    {
      "symbol": "SKHY",
      "relativeScore": 3.523,
      "aiScore": 53.02
    },
    {
      "symbol": "MU",
      "relativeScore": 2.6223,
      "aiScore": 52.82
    },
    {
      "symbol": "CL",
      "relativeScore": 0.9883,
      "aiScore": 51.15
    },
    {
      "symbol": "DRAM",
      "relativeScore": 2.5865,
      "aiScore": 50.1
    },
    {
      "symbol": "ETH",
      "relativeScore": -0.1492,
      "aiScore": 49.06
    },
    {
      "symbol": "HYPE",
      "relativeScore": 2.1567,
      "aiScore": 47.59
    },
    {
      "symbol": "XRP",
      "relativeScore": -0.6507,
      "aiScore": 46.3
    },
    {
      "symbol": "SOL",
      "relativeScore": -0.4344,
      "aiScore": 46.25
    },
    {
      "symbol": "SOXL",
      "relativeScore": 2.7024,
      "aiScore": 45.57
    },
    {
      "symbol": "XAU",
      "relativeScore": -0.7002,
      "aiScore": 44.55
    },
    {
      "symbol": "ZEC",
      "relativeScore": 0.0012,
      "aiScore": 43.95
    },
    {
      "symbol": "SKHYNIX",
      "relativeScore": 1.2845,
      "aiScore": 41.71
    },
    {
      "symbol": "XAG",
      "relativeScore": -0.7882,
      "aiScore": 41.53
    },
    {
      "symbol": "SPCX",
      "relativeScore": -0.2731,
      "aiScore": 41.23
    }
  ]
}
