{
  "scanTime": "2026-06-24T07:59:59.999000+00:00",
  "items": [
    {
      "symbol": "BEAT",
      "relativeScore": 10.8418,
      "aiScore": 90.36
    },
    {
      "symbol": "SKHYNIX",
      "relativeScore": 3.7157,
      "aiScore": 60.85
    },
    {
      "symbol": "DRAM",
      "relativeScore": 2.1336,
      "aiScore": 52.69
    },
    {
      "symbol": "MU",
      "relativeScore": 0.6721,
      "aiScore": 48.33
    },
    {
      "symbol": "HYPE",
      "relativeScore": 1.2241,
      "aiScore": 47.88
    },
    {
      "symbol": "XAU",
      "relativeScore": 0.3748,
      "aiScore": 47.42
    },
    {
      "symbol": "SNDK",
      "relativeScore": 1.3503,
      "aiScore": 46.95
    },
    {
      "symbol": "SOL",
      "relativeScore": -0.1412,
      "aiScore": 46.65
    },
    {
      "symbol": "ETH",
      "relativeScore": 0.5047,
      "aiScore": 46.58
    },
    {
      "symbol": "XRP",
      "relativeScore": -0.3641,
      "aiScore": 43.28
    },
    {
      "symbol": "XAG",
      "relativeScore": 0.4091,
      "aiScore": 43.11
    },
    {
      "symbol": "WLD",
      "relativeScore": 1.2362,
      "aiScore": 42.51
    },
    {
      "symbol": "SPCX",
      "relativeScore": 1.2171,
      "aiScore": 40.44
    },
    {
      "symbol": "SOXL",
      "relativeScore": 1.5697,
      "aiScore": 38.13
    },
    {
      "symbol": "CBRS",
      "relativeScore": -1.642,
      "aiScore": 32.8
    }
  ]
}
